Metadata-Version: 2.1
Name: odoo9-addon-account-mass-reconcile-by-purchase-line
Version: 9.0.1.0.0.99.dev65
Summary: Allows to reconcile based on the PO line
Home-page: https://github.com/OCA/bank-statement-reconcile
Author: Eficent, Odoo Community Association (OCA)
Author-email: support@odoo-community.org
License: AGPL-3
Platform: UNKNOWN
Classifier: Programming Language :: Python
Classifier: Framework :: Odoo
Classifier: Framework :: Odoo :: 9.0
Classifier: License :: OSI Approved :: GNU Affero General Public License v3
Requires-Python: ~=2.7
Requires-Dist: odoo9-addon-account-mass-reconcile
Requires-Dist: odoo9-addon-account-move-line-purchase-info
Requires-Dist: odoo (<9.1a,>=9.0a)
